pyfiguration/__init__.py
pyfiguration/cli.py
pyfiguration/configuration.py
pyfiguration/pyfiguration.py
pyfiguration/utils.py
tests/__init__.py
tests/test_cli_config.py
tests/test_cli_inspect_script.py
tests/test_configuration.py
tests/test_pyfiguration.py
tests/test_utils.py
pyfiguration-0.2.1.dist-info/LICENSE.md
pyfiguration-0.2.1.dist-info/METADATA
pyfiguration-0.2.1.dist-info/WHEEL
pyfiguration-0.2.1.dist-info/entry_points.txt
pyfiguration-0.2.1.dist-info/top_level.txt
pyfiguration-0.2.1.dist-info/RECORD
