Metadata-Version: 2.1
Name: pyfiguration
Version: 0.2.1
Summary: Smarter config for Python
Home-page: UNKNOWN
Author: Gijs Wobben
License: UNKNOWN
Platform: UNKNOWN
Classifier: Programming Language :: Python :: 3.7
Classifier: Programming Language :: Python :: 3.8
Classifier: License :: OSI Approved :: MIT License
Classifier: Operating System :: OS Independent
Requires-Python: >=3.7
Requires-Dist: pyyaml
